resemu/cli/main.py
resemu/generators/latex.py
resemu/generators/pdf.py
resemu/models/resume.py
resemu/models/utils.py
resemu/templates/engineering.tex.j2
resemu-0.2.0.dist-info/METADATA
resemu-0.2.0.dist-info/WHEEL
resemu-0.2.0.dist-info/entry_points.txt
resemu-0.2.0.dist-info/licenses/LICENSE
resemu-0.2.0.dist-info/RECORD
