Metadata-Version: 2.4
Name: resemu
Version: 0.2.0
Summary: Generate solid resumes from YAML data
Project-URL: Homepage, https://github.com/matheodrd/resemu
Project-URL: Documentation, https://github.com/matheodrd/resemu/blob/master/README.md
Project-URL: Repository, https://github.com/matheodrd/resemu
Project-URL: Issues, https://github.com/matheodrd/resemu/issues
Author: matheodrd
License-Expression: MIT
License-File: LICENSE
Keywords: CLI,LaTeX,PDF,YAML,resume
Classifier: Development Status :: 4 - Beta
Classifier: License :: OSI Approved :: MIT License
Classifier: Natural Language :: English
Classifier: Programming Language :: Python
Classifier: Programming Language :: Python :: 3
Classifier: Programming Language :: Python :: 3.12
Classifier: Topic :: Text Processing :: Markup :: LaTeX
Classifier: Topic :: Utilities
Classifier: Typing :: Typed
Requires-Python: >=3.12
Requires-Dist: jinja2>=3.1.6
Requires-Dist: pydantic[email]>=2.11.5
Requires-Dist: pyyaml>=6.0.2
Requires-Dist: rich>=14.0.0
Requires-Dist: typer>=0.16.0
